{
    "org.apache.cordova.statusbar": {
        "source": {
            "type": "registry",
            "id": "org.apache.cordova.statusbar"
        }
    },
    "org.apache.cordova.splashscreen": {
        "source": {
            "type": "registry",
            "id": "org.apache.cordova.splashscreen"
        }
    },
    "org.apache.cordova.dialogs": {
        "source": {
            "type": "registry",
            "id": "org.apache.cordova.dialogs"
        }
    },
    "org.apache.cordova.inappbrowser": {
        "source": {
            "type": "registry",
            "id": "org.apache.cordova.inappbrowser"
        }
    },
    "com.chariotsolutions.nfc.plugin": {
        "source": {
            "type": "git",
            "url": "https://github.com/chariotsolutions/phonegap-nfc.git",
            "subdir": "."
        }
    }
}